app.py
yooztech_mcp_api_request-0.0.3.dist-info/licenses/LICENSE
yooztech_mcp_api_request-0.0.3.dist-info/METADATA
yooztech_mcp_api_request-0.0.3.dist-info/WHEEL
yooztech_mcp_api_request-0.0.3.dist-info/entry_points.txt
yooztech_mcp_api_request-0.0.3.dist-info/top_level.txt
yooztech_mcp_api_request-0.0.3.dist-info/RECORD
