Metadata-Version: 2.4
Name: yooztech_mcp_api_request
Version: 0.0.3
Summary: MCP server template for generic API requests
Author: yooztech
License-Expression: MIT
Requires-Python: >=3.10
License-File: LICENSE
Requires-Dist: mcp>=1.2.0
Requires-Dist: httpx>=0.27.0
Requires-Dist: PyYAML>=6.0.2
Dynamic: license-file
